flet_config/__init__.py
flet_config/metaconfig.py
flet_config/setconfig.py
flet_config-0.0.3.dist-info/METADATA
flet_config-0.0.3.dist-info/WHEEL
flet_config-0.0.3.dist-info/top_level.txt
flet_config-0.0.3.dist-info/RECORD
